ultron/__init__.py
ultron/main_cli.py
ultron/autonomous/__init__.py
ultron/autonomous/agent.py
ultron/autonomous/config.py
ultron/autonomous/prompts.py
ultron/autonomous/tool_handler.py
ultron/autonomous/prompts/system_prompt.md
ultron/autonomous/tools/__init__.py
ultron/autonomous/tools/file_system.py
ultron/autonomous/tools/shell.py
ultron/autonomous/tools/static_analysis.py
ultron/autonomous/tools/utilities.py
ultron/core/__init__.py
ultron/core/caching.py
ultron/core/constants.py
ultron/core/ignorer.py
ultron/engine/__init__.py
ultron/engine/agent.py
ultron/engine/code_analyzer.py
ultron/engine/llm_code_analyzer.py
ultron/engine/reviewer.py
ultron/models/__init__.py
ultron/models/data_models.py
ultron/models/sarif_models.py
ultron/reporting/__init__.py
ultron/reporting/display.py
ultron/reporting/sarif_converter.py
ultron_ai-0.1.4.dist-info/licenses/LICENSE
ultron_ai-0.1.4.dist-info/METADATA
ultron_ai-0.1.4.dist-info/WHEEL
ultron_ai-0.1.4.dist-info/entry_points.txt
ultron_ai-0.1.4.dist-info/top_level.txt
ultron_ai-0.1.4.dist-info/RECORD
