Metadata-Version: 2.4
Name: ultron-ai
Version: 0.1.4
Summary: ⚡ ULTRON-AI: Advanced AI-powered code analysis with Chain of Thought and ReAct framework
Home-page: https://github.com/Xplo8E/ultron-ai
Author: Xplo8E
Author-email: xplo8e@outlook.com
License: GPL-3.0
Project-URL: Source, https://github.com/Xplo8E/ultron-ai
Project-URL: Tracker, https://github.com/Xplo8E/ultron-ai/issues
Keywords: sast code-analysis ai security vulnerability-scanner code-review devsecops auditing llm gemini ultron chain-of-thought react sarif
Classifier: Development Status :: 4 - Beta
Classifier: Intended Audience :: Developers
Classifier: Topic :: Scientific/Engineering :: Artificial Intelligence
Classifier: Intended Audience :: Information Technology
Classifier: Topic :: Software Development :: Quality Assurance
Classifier: Topic :: Security
Classifier: License :: OSI Approved :: GNU General Public License v3 (GPLv3)
Classifier: Programming Language :: Python :: 3
Classifier: Programming Language :: Python :: 3.10
Classifier: Programming Language :: Python :: 3.11
Classifier: Programming Language :: Python :: 3.12
Classifier: Operating System :: OS Independent
Classifier: Environment :: Console
Requires-Python: >=3.10
License-File: LICENSE
Requires-Dist: google-genai
Requires-Dist: google-api-core
Requires-Dist: python-dotenv
Requires-Dist: click
Requires-Dist: rich
Requires-Dist: pydantic
Requires-Dist: demjson3
Requires-Dist: networkx
Dynamic: author
Dynamic: author-email
Dynamic: classifier
Dynamic: description
Dynamic: description-content-type
Dynamic: home-page
Dynamic: keywords
Dynamic: license
Dynamic: license-file
Dynamic: project-url
Dynamic: requires-dist
Dynamic: requires-python
Dynamic: summary
